Workbook

Sheet Resumo
A1: Ipiranga · App Eventos · resumo da estimativa (14/10/2026)
A3: Caminho | B3: Horas totais | C3: Investimento | D3: Preço sugerido | E3: Prazo (semanas) | F3: O que resolve
A4: Referência · PWA do portal | B4: ='Referencia PWA'!C11 | C4: ='Referencia PWA'!D11 | D4: =ROUND(C4/1000,0)*1000 | E4: 3 | F4: Praticidade: ícone na tela, agenda e mapa offline, acesso direto ao evento. Sem push.
A5: Opção A · App da Convenção | B5: ='Opcao A - Convencao'!C15 | C5: ='Opcao A - Convencao'!D15 | D5: ='Opcao A - Convencao'!D16 | E5: ='Opcao A - Convencao'!C17 | F5: Tudo do PWA mais push notification e experiência nativa, para um evento por vez.
A6: Opção B · App Ipiranga Eventos | B6: ='Opcao B - Portal completo'!C15 | C6: ='Opcao B - Portal completo'!D15 | D6: ='Opcao B - Portal completo'!D16 | E6: ='Opcao B - Portal completo'!C17 | F6: App permanente para todos os eventos, inscrição completa pelo celular, push por evento e público.
A9: Prazos contam a partir do kick-off e não incluem o tempo de abertura das contas de desenvolvedor da Ipiranga (1 a 3 semanas, em paralelo) nem a revisão das lojas na primeira publicação (2 a 7 dias).

Sheet Premissas
A1: Ipiranga · App Eventos · premissas de precificação
A3: Parâmetro | B3: Valor | C3: Observação
A4: Valor hora (R$) | B4: 200 | C4: Mesma base do App de Execução (out/2026)
A5: Reserva técnica (% da execução) | B5: 0.1 | C5: Imprevistos de integração e revisão das lojas
A6: Direção (% da execução) | B6: 0.3 | C6: Bruno (produto/UX), Nóbrega (arquitetura), gestão, reuniões
A7: Fator total sobre execução | B7: =1+B5+B6 | C7: Horas faturadas = execução × fator
A8: Horas produtivas por semana (time) | B8: 60 | C8: 2 devs mobile/back em paralelo + design, média
A10: Como ler: cada aba de opção lista as horas de execução por frente. A reserva e a direção são calculadas sobre o total de execução; o preço é horas totais × valor hora.

Sheet Opcao A - Convencao
A1: Opção A · App da Convenção (um evento, escopo reduzido)
A2: App dedicado ao evento principal, reaproveitável para a próxima convenção com troca de conteúdo pelo portal.
A4: Frente | B4: Entregas | C4: Horas de execução | D4: R$ execução
A5: Descoberta e arquitetura | B5: Mapeamento da API que o portal precisa expor (login, evento, agenda, mapa, inscrição em arena), definição da stack híbrida (React Native/Expo), fluxo de dados offline, plano de push | C5: 24 | D5: =C5*Premissas!$B$4
A6: UX/UI mobile | B6: Design system mobile a partir da identidade do portal; cerca de 12 telas: onboarding/login, home do evento, agenda por dia com favoritos, detalhe de atividade, mapa do evento com pontos, inscrição em arena, perfil/credencial, central de avisos; protótipo navegável | C6: 60 | D6: =C6*Premissas!$B$4
A7: Backend e API no portal | B7: Autenticação por token, endpoints de evento, agenda, mapa, inscrição em arena, cadastro de dispositivo; painel de envio de push no admin do portal (texto, público, agendamento) | C7: 60 | D7: =C7*Premissas!$B$4
A8: App mobile (iOS e Android) | B8: Setup do projeto, login integrado, home, agenda com favoritos e lembretes, mapa com zoom e pontos de interesse, inscrição em arena, perfil, central de avisos, cache offline de agenda e mapa, recebimento de push, deep link por e-mail/QR | C8: 150 | D8: =C8*Premissas!$B$4
A9: Push notification | B9: Integração FCM/APNs, registro de dispositivos, segmentação por evento e perfil (revendedor/funcionário), histórico de envios | C9: 20 | D9: =C9*Premissas!$B$4
A10: QA e homologação | B10: Testes em dispositivos iOS e Android, cenários sem conexão, matriz de versões de sistema, correções; rodada de homologação com a Ipiranga via TestFlight e APK | C10: 36 | D10: =C10*Premissas!$B$4
A11: Publicação nas lojas | B11: Contas de desenvolvedor da Ipiranga, assets de loja, política de privacidade, formulários de dados, submissão e resposta às revisões Apple e Google | C11: 20 | D11: =C11*Premissas!$B$4
A12: Execução | C12: =SUM(C5:C11) | D12: =C12*Premissas!$B$4
A13: Reserva técnica | C13: =C12*Premissas!$B$5 | D13: =C13*Premissas!$B$4
A14: Direção e gestão | C14: =C12*Premissas!$B$6 | D14: =C14*Premissas!$B$4
A15: TOTAL | C15: =SUM(C12:C14) | D15: =C15*Premissas!$B$4
A16: Preço sugerido (arredondado) | D16: =ROUND(D15/1000,0)*1000
A17: Prazo estimado (semanas) | C17: =ROUNDUP(C15/Premissas!$B$8,0)
A18: Pagamento sugerido
A19: 30% na assinatura | D19: =D16*0.3
A20: 30% na homologação (TestFlight / APK interno) | D20: =D16*0.3
A21: 40% na publicação nas lojas | D21: =D16*0.4

Sheet Opcao B - Portal completo
A1: Opção B · App de todos os eventos do portal
A2: Um app permanente da Ipiranga Eventos, que acompanha qualquer evento criado no portal.
A4: Frente | B4: Entregas | C4: Horas de execução | D4: R$ execução
A5: Descoberta e arquitetura | B5: Tudo da opção A, mais modelagem dos formulários dinâmicos de inscrição do portal (campos, regras, anexos, passagens e hotelaria quando houver), lista de eventos e perfis de acesso | C5: 32 | D5: =C5*Premissas!$B$4
A6: UX/UI mobile | B6: Cerca de 22 telas: além das telas da opção A, lista e filtro de eventos, detalhe de evento, fluxo completo de inscrição com formulários dinâmicos, meus eventos e histórico, documentos e materiais do evento, preferências de notificação | C6: 100 | D6: =C6*Premissas!$B$4
A7: Backend e API no portal | B7: API completa: catálogo de eventos, inscrições com formulários dinâmicos e validações, materiais e documentos, perfil e histórico, notificações por evento; painel de push por evento e por público | C7: 110 | D7: =C7*Premissas!$B$4
A8: App mobile (iOS e Android) | B8: Tudo da opção A para qualquer evento, renderizador de formulários dinâmicos, upload de documentos, meus eventos, materiais, preferências; compatível com a estrutura atual de eventos do portal sem retrabalho por evento | C8: 260 | D8: =C8*Premissas!$B$4
A9: Push notification | B9: Integração FCM/APNs, segmentação por evento, público e etapa da jornada (inscrito, confirmado, presente), agendamento e histórico | C9: 30 | D9: =C9*Premissas!$B$4
A10: QA e homologação | B10: Matriz maior de cenários (vários eventos, formulários distintos, offline), testes em dispositivos, rodadas de homologação com a Ipiranga | C10: 56 | D10: =C10*Premissas!$B$4
A11: Publicação nas lojas | B11: Igual à opção A | C11: 20 | D11: =C11*Premissas!$B$4
A12: Execução | C12: =SUM(C5:C11) | D12: =C12*Premissas!$B$4
A13: Reserva técnica | C13: =C12*Premissas!$B$5 | D13: =C13*Premissas!$B$4
A14: Direção e gestão | C14: =C12*Premissas!$B$6 | D14: =C14*Premissas!$B$4
A15: TOTAL | C15: =SUM(C12:C14) | D15: =C15*Premissas!$B$4
A16: Preço sugerido (arredondado) | D16: =ROUND(D15/1000,0)*1000
A17: Prazo estimado (semanas) | C17: =ROUNDUP(C15/Premissas!$B$8,0)
A18: Pagamento sugerido
A19: 30% na assinatura | D19: =D16*0.3
A20: 30% na homologação (TestFlight / APK interno) | D20: =D16*0.3
A21: 40% na publicação nas lojas | D21: =D16*0.4

Sheet Referencia PWA
A1: Referência · evolução PWA do portal (caminho em teste)
A2: Não é a estimativa pedida; serve para comparar o custo de levar o portal até o limite do que o PWA permite.
A4: Frente | B4: Entregas | C4: Horas de execução | D4: R$ execução
A5: Manifesto e instalação | B5: Ícone na tela inicial, splash, modo standalone, orientação de instalação no iOS e Android dentro do fluxo de inscrição | C5: 12 | D5: =C5*Premissas!$B$4
A6: Offline | B6: Service worker com cache de agenda, mapa e credencial do evento; estados sem conexão | C6: 20 | D6: =C6*Premissas!$B$4
A7: Interface mobile do evento | B7: Revisão da experiência no celular: home do evento, agenda, mapa com zoom, atalhos; login que cai direto no evento | C7: 40 | D7: =C7*Premissas!$B$4
A8: Salvar no calendário | B8: Função fixa no portal e na mensagem de sucesso (já em andamento, fora desta conta) | C8: 0 | D8: =C8*Premissas!$B$4
A9: Piloto com a estrutura da Convenção 2025 | B9: Levantar o evento em homologação, rodada de uso com a Ipiranga, ajustes | C9: 16 | D9: =C9*Premissas!$B$4
A10: Execução | C10: =SUM(C5:C9) | D10: =C10*Premissas!$B$4
A11: Com reserva e direção | C11: =C10*Premissas!$B$7 | D11: =C11*Premissas!$B$4

Sheet Recorrentes
A1: Custos recorrentes de um app nativo (fora do investimento de construção)
A3: Item | B3: Quem paga | C3: Valor | D3: Periodicidade | E3: Observação
A4: Apple Developer Program | B4: Ipiranga | C4: US$ 99 | D4: anual | E4: Conta da empresa, exige D-U-N-S; prazo de aprovação da conta de 1 a 3 semanas
A5: Google Play Console | B5: Ipiranga | C5: US$ 25 | D5: única | E5: Conta da empresa; verificação de identidade
A6: Push (Firebase Cloud Messaging) | B6: Ipiranga | C6: sem custo | D6: mensal | E6: Volume de eventos cabe no plano gratuito
A7: Sustentação do app | B7: Fattoria | C7: =10*Premissas!$B$4 | D7: mensal, mínimo | E7: 10 h/mês: atualizações de sistema operacional, bibliotecas, revisões de loja, pequenos ajustes. Picos de evento fora da base
A8: Sustentação do app | B8: Fattoria | C8: =16*Premissas!$B$4 | D8: mensal, confortável | E8: 16 h/mês cobre também evolução leve entre eventos
A9: Hospedagem e API do portal | B9: Ipiranga | C9: incluída | D9: mensal | E9: Já coberta pela operação atual do portal; a API acrescenta carga marginal
